LICENSE.txt
MANIFEST.in
README.md
setup.cfg
setup.py
facebooktoken/__init__.py
facebooktoken/base.py
facebooktoken.egg-info/PKG-INFO
facebooktoken.egg-info/SOURCES.txt
facebooktoken.egg-info/dependency_links.txt
facebooktoken.egg-info/not-zip-safe
facebooktoken.egg-info/requires.txt
facebooktoken.egg-info/top_level.txt