Metadata-Version: 1.0
Name: facebooktoken
Version: 0.0.1
Summary: Lightweight library for refreshing your facebook access token.
Home-page: https://github.com/iktw/python-facebook-token
Author: Mohammed Hammoud
Author-email: mohammed@iktw.se
License: MIT licence, see LICENCE.txt
Platform: UNKNOWN
